pynytimes/__init__.py
pynytimes/__version__.py
pynytimes/api.py
pynytimes/helpers/__init__.py
pynytimes/helpers/article_metadata.py
pynytimes/helpers/article_search.py
pynytimes/helpers/best_sellers.py
pynytimes/helpers/book_reviews.py
pynytimes/helpers/dates.py
pynytimes/helpers/latest_articles.py
pynytimes/helpers/load_data.py
pynytimes/helpers/most_shared.py
pynytimes/helpers/most_viewed.py
pynytimes/helpers/movie_reviews.py
pynytimes/helpers/tag_query.py
pynytimes-0.10.0.dist-info/LICENSE
pynytimes-0.10.0.dist-info/METADATA
pynytimes-0.10.0.dist-info/WHEEL
pynytimes-0.10.0.dist-info/top_level.txt
pynytimes-0.10.0.dist-info/RECORD
