Metadata-Version: 2.1
Name: pynytimes
Version: 0.10.0
Summary: A Python wrapper for (most) New York Times APIs
Home-page: https://pynytimes.michadenheijer.com/
Author: Micha den Heijer
Author-email: micha@michadenheijer.com
License: MIT
Classifier: License :: OSI Approved :: MIT License
Classifier: Development Status :: 5 - Production/Stable
Classifier: Intended Audience :: Developers
Classifier: Intended Audience :: Information Technology
Classifier: Intended Audience :: Science/Research
Classifier: Natural Language :: English
Classifier: Programming Language :: Python :: 3.9
Classifier: Programming Language :: Python :: 3.10
Classifier: Programming Language :: Python :: 3.11
Classifier: Programming Language :: Python :: 3.12
Classifier: Programming Language :: Python :: Implementation :: CPython
Classifier: Programming Language :: Python :: Implementation :: PyPy
Classifier: Topic :: Sociology
Requires-Python: >=3.9, <4
License-File: LICENSE
